{
  "manifests": {
    "luckyseven/services": {
      "manifest": {
        "bundles": {
          "Luckyseven\\Bundle\\LuckysevenServicesBundle\\LuckysevenServicesBundle": [
            "all"
          ]
        },
        "copy-from-package": {
          "src/Entity/Service.php": "%SRC_DIR%/Entity/Service.php",
          "src/Entity/EntityService.php": "%SRC_DIR%/Entity/EntityService.php",
          "src/Repository/ServiceRespository.php": "%SRC_DIR%/Repository/ServiceRespository.php",
          "src/Repository/EntityServiceRespository.php": "%SRC_DIR%/Repository/EntityServiceRespository.php"
        }
      },
      "ref": "5b2157fed13546fec5765e42f552ad36529a07a7"
    }
  }
}
